db_builders/__init__.py
db_builders/base_search.py
db_builders/llm.py
db_builders/loading.py
db_builders/utils.py
db_builders/omniclass/__init__.py
db_builders/omniclass/builder_functions.py
db_builders/omniclass/chains.py
db_builders/omniclass/runtime.py
db_builders/omniclass/prompts/PARAMETER_PROMPT.txt
db_builders/omniclass/prompts/VALUE_PROMPT.txt
db_builders/search/__init__.py
db_builders/search/manufacturer_checker.py
db_builders/search/name_extractor.py
db_builders/search/runtime.py
db_builders/search/search_handler.py
db_builders/search/site_checker.py
db_builders/typedefs/__init__.py
db_builders/typedefs/manufacturer.py
db_builders/typedefs/omniclass.py
db_builders/typedefs/parameter.py
db_builders/typedefs/search_result.py
db_builders-0.0.5.dist-info/METADATA
db_builders-0.0.5.dist-info/WHEEL
db_builders-0.0.5.dist-info/top_level.txt
db_builders-0.0.5.dist-info/RECORD
